sonetel/__init__.py
sonetel/_constants.py
sonetel/account.py
sonetel/auth.py
sonetel/calls.py
sonetel/exceptions.py
sonetel/phonenumber.py
sonetel/recording.py
sonetel/users.py
sonetel/utilities.py
sonetel/voiceapps.py
sonetel-0.2.1.dist-info/LICENSE
sonetel-0.2.1.dist-info/METADATA
sonetel-0.2.1.dist-info/WHEEL
sonetel-0.2.1.dist-info/top_level.txt
sonetel-0.2.1.dist-info/RECORD
