Metadata-Version: 2.1
Name: sonetel
Version: 0.2.1
Summary: A simple python wrapper for using Sonetel's REST APIs
Home-page: https://github.com/Sonetel/sonetel-python
Author: aashish
Author-email: dev.support@sonetel.com
License: MIT
Project-URL: Bug Tracker, https://github.com/Sonetel/sonetel-python/issues
Classifier: Programming Language :: Python :: 3
Classifier: Operating System :: Microsoft :: Windows
Classifier: Operating System :: POSIX :: Linux
Classifier: Development Status :: 3 - Alpha
Classifier: Intended Audience :: Developers
Classifier: Intended Audience :: Telecommunications Industry
Classifier: Topic :: Communications
Classifier: Topic :: Communications :: Telephony
Classifier: Topic :: Software Development :: Libraries :: Python Modules
Classifier: License :: OSI Approved :: MIT License
Requires-Python: >=3.6
License-File: LICENSE
Requires-Dist: requests
Requires-Dist: pyjwt[crypto]
